biotraj/.gitignore
biotraj/__init__.py
biotraj/dcd.cp310-win_amd64.pyd
biotraj/dcd.pyx
biotraj/dcdlib.pxd
biotraj/netcdf.py
biotraj/trr.cp310-win_amd64.pyd
biotraj/trr.pyx
biotraj/trrlib.pxd
biotraj/utils.py
biotraj/version.py
biotraj/xdrlib.pxd
biotraj/xtc.cp310-win_amd64.pyd
biotraj/xtc.pyx
biotraj/include/dcdplugin.h
biotraj/include/endianswap.h
biotraj/include/fastio.h
biotraj/include/largefiles.h
biotraj/include/molfile_plugin.h
biotraj/include/trr_header.h
biotraj/include/vmdplugin.h
biotraj/include/xdr_seek.h
biotraj/include/xdrfile.h
biotraj/include/xdrfile_trr.h
biotraj/include/xdrfile_xtc.h
biotraj/src/.gitignore
biotraj/src/README
biotraj/src/dcdplugin.c
biotraj/src/dcdplugin.license
biotraj/src/xdr_seek.c
biotraj/src/xdrfile.c
biotraj/src/xdrfile_trr.c
biotraj/src/xdrfile_xtc.c
biotraj-1.2.2.dist-info/LICENSE.rst
biotraj-1.2.2.dist-info/METADATA
biotraj-1.2.2.dist-info/WHEEL
biotraj-1.2.2.dist-info/top_level.txt
biotraj-1.2.2.dist-info/RECORD
