Metadata-Version: 2.1
Name: biotraj
Version: 1.2.2
Summary: Basic trajectory file format functionality for Biotite; forked from MDTraj
Author: Robert McGibbon, The Biotite contributors
License: GNU LESSER GENERAL PUBLIC LICENSE
Project-URL: homepage, https://www.biotite-python.org
Project-URL: repository, https://github.com/biotite-dev/biotraj
Project-URL: documentation, https://www.biotite-python.org
Classifier: Development Status :: 4 - Beta
Classifier: Intended Audience :: Developers
Classifier: Intended Audience :: Science/Research
Classifier: License :: OSI Approved :: GNU Lesser General Public License v2 or later (LGPLv2+)
Classifier: Natural Language :: English
Classifier: Operating System :: POSIX :: Linux
Classifier: Operating System :: MacOS
Classifier: Operating System :: Microsoft :: Windows
Classifier: Programming Language :: Python :: 3
Classifier: Programming Language :: Python :: Implementation :: CPython
Classifier: Topic :: Scientific/Engineering :: Bio-Informatics
Requires-Python: >=3.10
License-File: LICENSE.rst
Requires-Dist: numpy>=1.25
Requires-Dist: scipy>=1.13
Provides-Extra: lint
Requires-Dist: ruff==0.6.1; extra == "lint"
Provides-Extra: test
Requires-Dist: pytest; extra == "test"
Requires-Dist: psutil; extra == "test"
Requires-Dist: netcdf4>=1.7.1; extra == "test"
